crux_odin/__init__.py
crux_odin/dataclass.py
crux_odin/dict_utils.py
crux_odin/types/deadlines.py
crux_odin/validate_yaml.py
crux_odin/validations/deadlines.py
crux_odin/validations/valid_timezones.py
crux_odin/workflow_crd.yaml
crux_odin-1.12.0.dist-info/METADATA
crux_odin-1.12.0.dist-info/WHEEL
crux_odin-1.12.0.dist-info/RECORD
