Metadata-Version: 2.3
Name: crux-odin
Version: 1.12.0
Summary: Open Data Integration Nomenclature (ODIN) is Crux’s standard for declarative data delivery
Author: Crux Data
Author-email: help@cruxdata.com
Requires-Python: >=3.8.1
Classifier: Programming Language :: Python :: 3
Classifier: Programming Language :: Python :: 3.9
Classifier: Programming Language :: Python :: 3.10
Classifier: Programming Language :: Python :: 3.11
Classifier: Programming Language :: Python :: 3.12
Classifier: Programming Language :: Python :: 3.13
Requires-Dist: croniter (>=0.3.18)
Requires-Dist: jsonschema
Requires-Dist: poethepoet
Requires-Dist: pydantic
Requires-Dist: pytest-cov
Requires-Dist: pyyaml
Requires-Dist: ruamel-yaml
